colorby/__init__.py
colorby-1.0.0.dist-info/licenses/LICENSE
colorby-1.0.0.dist-info/WHEEL
colorby-1.0.0.dist-info/entry_points.txt
colorby-1.0.0.dist-info/METADATA
colorby-1.0.0.dist-info/RECORD
