Metadata-Version: 2.4
Name: colorby
Version: 1.0.0
Summary: CLI for coloring lines from stdin based on a key identified by a regular expression
Author: Colin Chan
Author-email: Colin Chan <colin+colorby@lumeh.org>
License-Expression: MIT
License-File: LICENSE
Classifier: Development Status :: 5 - Production/Stable
Classifier: Environment :: Console
Classifier: Operating System :: POSIX
Classifier: Programming Language :: Python :: 3
Classifier: Topic :: Utilities
Requires-Python: >=3.11
Project-URL: Homepage, https://www.lumeh.org/projects/colorby/
Project-URL: Issues, https://github.com/kalgynirae/colorby/issues
